{
  "sections": {
    "intro": "簡介",
    "part1": "第一部｜核心理念與哲學基礎"
  },
  "0": {
    "title": "簡介",
    "summary": "自然幣是一種全新的貨幣哲學，以循環、腐敗、共振為核心...",
    "body": [
      "貨幣不是數字，而是關係。
人不是孤島，而是流動的節點。
自然不是背景，而是整個舞台。」

1｜人的定義：不只是生存的個體

在資本主義裡，人被定義為 勞動力 或 消費者。

在福利制度裡，人被定義為 需要保障的存在。

在自然幣的語境中，人被重新定義為：

    共振的源頭：每一個行為都可能產生迴響。
    流動的節點：不斷在社會網絡中交換能量。
    不可被簡化為數字的存在：價值不是薪資，而是影響與回響。

👉 人的價值 ≠ 僅限於市場價格。

2｜貨幣的定義：不只是積累的數字

在傳統貨幣體系中，貨幣被視為 價值的儲存與交換工具。

問題在於：當貨幣永不衰敗，它會逐漸脫離流動，成為壓迫的工具。

自然幣重新定義貨幣：

    貨幣是一種能量：像水與空氣，需要流動才能存在。
    貨幣會腐敗：囤積會加速貶損，唯有流動才延續價值。
    貨幣與共振連結：幣值不是由稀缺決定，而是由迴響強度決定。

👉 貨幣不再是「重量」，而是「呼吸」。

3｜自然的定義：不只是資源庫存

現代經濟把自然當作 原料庫：可以被無限開採與消耗。

自然幣視自然為：

    循環的節律：腐敗與再生的源頭。
    經濟的參與者：森林、海洋、氣候的變化，必須計入系統。
    價值的對照：當貨幣脫離自然節律，它將失去真實性。

👉 自然不是舞台外的背景，而是價值網絡的一部分。

4｜三元重構：人・貨幣・自然的共生關係

傳統體系的定義：

    人為了貨幣工作；
    貨幣以自然為代價；
    自然被消耗殆盡。

自然幣的重構：

    人 → 共振的節點
    貨幣 → 循環的能量
    自然 → 秩序的參照

這三者不再是壓迫與被壓迫的鏈條，而是 共生的三角結構。

🧭 小結

自然幣的第一步，不是技術設計，而是 定義的重構：

    人不再是勞動的影子；
    貨幣不再是囤積的鎖鏈；
    自然不再是沉默的犧牲品。

人・貨幣・自然 —— 三元合一，才能重新書寫未來的價值語言。",
      "這種循環反映自然的規律：生長、腐敗、再生。透過這種節奏，自然幣防止壟斷並回報不可見的社會貢獻。"
    ]
  },
  "1": {
    "title": "第一章｜核心定義：人・貨幣・自然",
    "summary": "定義「人・貨幣・自然」三元關係...",
    "body": [
      "第一個核心定義指出：人類是價值的主體，貨幣是交換的媒介，自然是價值的根基。",
      "這三元關係構成自然幣的哲學基礎，將人類社會與生態平衡緊密連結。"
    ]
  },
  "2": {
    "title": "第二章｜自然幣導論：流動與腐敗",
    "summary": "介紹自然幣如何以流動、腐敗、共振為核心，對照傳統資本邏輯。"
  },
  "3": {
    "title": "第三章｜資本主義的盲點：壟斷、囤積與無形價值",
    "summary": "揭示資本主義的盲點：壟斷、囤積，以及對無形社會貢獻的低估。"
  },
  "4": {
    "title": "第四章｜循環主義：經濟的新詩學",
    "summary": "提出循環主義作為新的經濟詩學，強調運動、再生與互惠。"
  },
  "5": {
    "title": "第五章｜與資本主義、福利主義、社會主義的比較",
    "summary": "比較自然幣框架與資本主義、福利主義、社會主義，突顯其互補性。"
  },
  "6": {
    "title": "第六章｜自然幣七條鐵律",
    "summary": "闡述自然幣的七條鐵律，界定其核心治理原則。"
  },
  "7": {
    "title": "第七章｜宣言與信念條款",
    "summary": "建立宣言與信念條款，將自然幣同時定位為制度與哲學。"
  },
  "8": {
    "title": "第八章｜腐敗與反壟斷機制",
    "summary": "解釋腐敗與反壟斷機制，防止資產過度集中。"
  },
  "9": {
    "title": "第九章｜時間性腐敗（FreshDecay）",
    "summary": "介紹時間性腐敗（FreshDecay）原則，強迫貨幣保持流動。"
  },
  "10": {
    "title": "第十章｜散值 + 新鮮度模型整合",
    "summary": "展示散值與新鮮度模型的整合，結合反壟斷與反囤積規則。"
  },
  "11": {
    "title": "第十一章｜貨幣與時間：第四維度",
    "summary": "重新詮釋貨幣作為一種時間媒介，將價值與第四維度綁定。"
  }
}
